lepton_jpeg_python-0.5.5.dist-info/METADATA
lepton_jpeg_python-0.5.5.dist-info/WHEEL
lepton_jpeg_python/__init__.py
lepton_jpeg_python/lepton_jpeg_python.cpython-313-x86_64-linux-gnu.so
lepton_jpeg_python-0.5.5.dist-info/RECORD
