Metadata-Version: 2.4
Name: lepton_jpeg_python
Version: 0.5.5
Classifier: Programming Language :: Python :: 3
Classifier: Programming Language :: Rust
Classifier: Operating System :: OS Independent
Summary: Rust port of the Lepton JPEG compression library
Author-email: Kristof Roomp   <kristofr@gmail.com>
License-Expression: Apache-2.0
Requires-Python: >=3.8
Project-URL: Homepage, https://github.com/microsoft/lepton_jpeg_rust
